safe_regex/__init__.py
safe_regex/regular_expression.py
safe_regex-0.1.dist-info/LICENSE
safe_regex-0.1.dist-info/METADATA
safe_regex-0.1.dist-info/WHEEL
safe_regex-0.1.dist-info/top_level.txt
safe_regex-0.1.dist-info/RECORD
