Metadata-Version: 2.1
Name: safe-regex
Version: 0.1
Summary: Embeds unit tests with regular expressions
Home-page: https://github.com/ensslen/safe-regex
Author: Steven Ensslen
Author-email: steven@claritycloudworks.com
License: UNKNOWN
Keywords: test,regular expression
Platform: UNKNOWN
Classifier: Programming Language :: Python :: 3
Classifier: Operating System :: OS Independent
Requires-Dist: pydantic (<2)
Requires-Dist: pyyaml (<6)
